py_term_helpers/__init__.py
py_term_helpers-0.0.7.dist-info/METADATA
py_term_helpers-0.0.7.dist-info/WHEEL
py_term_helpers-0.0.7.dist-info/licenses/LICENSE
py_term_helpers-0.0.7.dist-info/RECORD
