Metadata-Version: 2.3
Name: py_term_helpers
Version: 0.0.7
Summary: A simple package for helpful python terminal outputs
Project-URL: Homepage, https://github.com/rothberry/py-term-helpers
Project-URL: Issues, https://github.com/rothberry/py-term-helpers/issues
Author-email: rothberry <phil.roth077@gmail.com>
License-File: LICENSE
Classifier: License :: OSI Approved :: MIT License
Classifier: Operating System :: OS Independent
Classifier: Programming Language :: Python :: 3
Requires-Python: >=3.8
